reader/__init__.py
reader/model.py
real_kumarmodel-0.0.1.dist-info/METADATA
real_kumarmodel-0.0.1.dist-info/WHEEL
real_kumarmodel-0.0.1.dist-info/top_level.txt
real_kumarmodel-0.0.1.dist-info/RECORD
