Metadata-Version: 2.1
Name: real-kumarmodel
Version: 0.0.1
Summary: load csv.
Home-page: UNKNOWN
Author: Kumar Awanish
Author-email: awanish00@gmail.com
License: MIT
Platform: UNKNOWN
Classifier: Development Status :: 4 - Beta
Classifier: License :: OSI Approved :: MIT License
Classifier: Programming Language :: Python
Classifier: Programming Language :: Python :: 3.5
Classifier: Programming Language :: Python :: 3.6
Classifier: Topic :: Software Development :: Libraries
Classifier: Topic :: Software Development :: Libraries :: Python Modules
Classifier: Intended Audience :: Developers
Requires-Python: >=3.5
Requires-Dist: pandas
Requires-Dist: scikit-learn
